LICENSE
gordo_client/__init__.py
gordo_client/cli/__init__.py
gordo_client/cli/client.py
gordo_client/cli/custom_types.py
gordo_client/client.py
gordo_client/dataframe.py
gordo_client/dist.py
gordo_client/forwarders.py
gordo_client/io.py
gordo_client/schemas.py
gordo_client/utils.py
gordo_client-6.3.0.dist-info/LICENSE
gordo_client-6.3.0.dist-info/METADATA
gordo_client-6.3.0.dist-info/WHEEL
gordo_client-6.3.0.dist-info/entry_points.txt
gordo_client-6.3.0.dist-info/RECORD
