Metadata-Version: 2.1
Name: gordo-client
Version: 6.3.0
Summary: Gordo client
Home-page: https://github.com/equinor/gordo-client
License: AGPL-3.0
Keywords: gordo-client
Author: Equinor ASA
Author-email: fg_gpl@equinor.com
Requires-Python: >=3.9,<4.0
Classifier: Intended Audience :: Developers
Classifier: License :: OSI Approved :: GNU Affero General Public License v3
Classifier: Natural Language :: English
Classifier: Programming Language :: Python :: 3
Classifier: Programming Language :: Python :: 3.9
Classifier: Programming Language :: Python :: 3.10
Classifier: Programming Language :: Python :: 3.11
Classifier: Programming Language :: Python :: 3 :: Only
Classifier: Programming Language :: Python :: 3.10
Classifier: Programming Language :: Python :: 3.9
Classifier: Topic :: Scientific/Engineering
Classifier: Topic :: Software Development
Requires-Dist: PyYAML (>=5.3.1,<7)
Requires-Dist: click (>=7.0.0,<9.0.0)
Requires-Dist: gordo-core (>=0.3.5,<0.4.0)
Requires-Dist: pydantic (>=1.8.2,<2.0.0)
Requires-Dist: requests (>=2.20,<3.0)
Requires-Dist: simplejson (>=3.17.2,<4.0.0)
Requires-Dist: wrapt (>=1.11.0,<2.0.0)
Project-URL: Repository, https://github.com/equinor/gordo-client
